{"avatar_url":"https:\/\/avatars0.githubusercontent.com\/u\/3189403?v=4","author":"degaray","created":1,"closed":1,"merged":0,"rejected":1,"acceptance_rate":"0%","_pull_requests":{"9436":{"created":"2017-04-27T18:56:25Z","author":"degaray","html_url":"https:\/\/github.com\/magento\/magento2\/pull\/9436","repo":"magento\/magento2","state":"closed","title":"Reset password failure count when flag is expired PR-BUGFIXES-4432"}},"_issues":{"9218":{"created":"2017-04-12T12:37:12Z","html_url":"https:\/\/github.com\/magento\/magento2\/issues\/9218","repo":"magento\/magento2","state":"closed","title":"Module for external API's connection at checkout"},"8027":{"created":"2017-01-04T10:43:47Z","html_url":"https:\/\/github.com\/magento\/magento2\/issues\/8027","repo":"magento\/magento2","state":"closed","title":"There is no webapi resource for newsletter registration"}}}