{"avatar_url":"https:\/\/avatars1.githubusercontent.com\/u\/2716794?v=4","author":"keradus","created":3,"closed":3,"merged":1,"rejected":2,"acceptance_rate":"33%","_pull_requests":{"12192":{"created":"2017-11-11T13:36:31Z","author":"keradus","html_url":"https:\/\/github.com\/magento\/magento2\/pull\/12192","repo":"magento\/magento2","state":"closed","title":"CS: reapply fixers"},"8823":{"created":"2017-03-08T19:46:26Z","author":"keradus","html_url":"https:\/\/github.com\/magento\/magento2\/pull\/8823","repo":"magento\/magento2","state":"closed","title":"Upgrade PHP CS Fixer to v2 + re-apply"},"8822":{"created":"2017-03-08T19:45:28Z","author":"keradus","html_url":"https:\/\/github.com\/magento\/magento2\/pull\/8822","repo":"magento\/magento2","state":"merged","title":"Upgrade PHP CS Fixer to v2"}},"_issues":[]}