{"avatar_url":"https:\/\/avatars0.githubusercontent.com\/u\/32677673?v=4","author":"nemesis-back","created":4,"closed":3,"merged":2,"rejected":1,"acceptance_rate":"67%","_pull_requests":{"12368":{"created":"2017-11-20T18:05:53Z","author":"nemesis-back","html_url":"https:\/\/github.com\/magento\/magento2\/pull\/12368","repo":"magento\/magento2","state":"merged","title":"[Backport for 2.1 of #9904] #8069: Saving Category with existing imag\u2026"},"11879":{"created":"2017-10-30T16:37:53Z","author":"nemesis-back","html_url":"https:\/\/github.com\/magento\/magento2\/pull\/11879","repo":"magento\/magento2","state":"merged","title":"#4004: Newsletter Subscriber create-date not set, and change_status_at broken "},"11852":{"created":"2017-10-29T19:45:50Z","author":"nemesis-back","html_url":"https:\/\/github.com\/magento\/magento2\/pull\/11852","repo":"magento\/magento2","state":"closed","title":"#10440: Missing $debugHintsPath when sending email via command line"},"11748":{"created":"2017-10-25T21:45:06Z","author":"nemesis-back","html_url":"https:\/\/github.com\/magento\/magento2\/pull\/11748","repo":"magento\/magento2","state":"closed","title":"#7778: Date of Birth attribute gets weird format on page reload"}},"_issues":[]}