{"avatar_url":"https:\/\/avatars3.githubusercontent.com\/u\/618218?v=4","author":"netzkollektiv","created":1,"closed":1,"merged":1,"rejected":0,"acceptance_rate":"100%","_pull_requests":{"10789":{"created":"2017-09-06T08:31:01Z","author":"netzkollektiv","html_url":"https:\/\/github.com\/magento\/magento2\/pull\/10789","repo":"magento\/magento2","state":"merged","title":"enable universal use of modal and tab_group"}},"_issues":{"10735":{"created":"2017-09-01T09:38:34Z","html_url":"https:\/\/github.com\/magento\/magento2\/issues\/10735","repo":"magento\/magento2","state":"closed","title":"dynamic-rows \/ dynamic-rows-grid components are missing prototype \/ legacy dependency "}}}