{"avatar_url":"https:\/\/avatars3.githubusercontent.com\/u\/22593218?v=4","author":"p-bystritsky","created":13,"closed":12,"merged":8,"rejected":4,"acceptance_rate":"67%","_pull_requests":{"12283":{"created":"2017-11-15T13:38:53Z","author":"p-bystritsky","html_url":"https:\/\/github.com\/magento\/magento2\/pull\/12283","repo":"magento\/magento2","state":"merged","title":"magento\/magento2#12083: Cannot import zero (0) value into custom attribute"},"12234":{"created":"2017-11-14T09:33:06Z","author":"p-bystritsky","html_url":"https:\/\/github.com\/magento\/magento2\/pull\/12234","repo":"magento\/magento2","state":"closed","title":"magento\/magento2#12163: UPS Shipping not listed in REST"},"12166":{"created":"2017-11-10T08:42:06Z","author":"p-bystritsky","html_url":"https:\/\/github.com\/magento\/magento2\/pull\/12166","repo":"magento\/magento2","state":"closed","title":"Removed"},"12107":{"created":"2017-11-08T12:43:32Z","author":"p-bystritsky","html_url":"https:\/\/github.com\/magento\/magento2\/pull\/12107","repo":"magento\/magento2","state":"merged","title":"magento\/magento2#11880: Configurable::getUsedProducts returns a different array after product collections is cached"},"12057":{"created":"2017-11-06T12:28:19Z","author":"p-bystritsky","html_url":"https:\/\/github.com\/magento\/magento2\/pull\/12057","repo":"magento\/magento2","state":"merged","title":"[Backport] magento\/magento2#9961: Unused product attributes display with value N\/A or NO on storefront."},"12003":{"created":"2017-11-03T15:32:40Z","author":"p-bystritsky","html_url":"https:\/\/github.com\/magento\/magento2\/pull\/12003","repo":"magento\/magento2","state":"merged","title":"magento\/magento2#11691: Wrong return type for getAttributeText($attributeCode)"},"12002":{"created":"2017-11-03T15:21:29Z","author":"p-bystritsky","html_url":"https:\/\/github.com\/magento\/magento2\/pull\/12002","repo":"magento\/magento2","state":"closed","title":"Duplicate"},"11994":{"created":"2017-11-03T12:44:57Z","author":"p-bystritsky","html_url":"https:\/\/github.com\/magento\/magento2\/pull\/11994","repo":"magento\/magento2","state":"closed","title":"Removed"},"11937":{"created":"2017-11-01T15:09:52Z","author":"p-bystritsky","html_url":"https:\/\/github.com\/magento\/magento2\/pull\/11937","repo":"magento\/magento2","state":"closed","title":"magento\/magento2#9002: Anchor categories are showing products of disabled subcategories."},"11876":{"created":"2017-10-30T14:40:05Z","author":"p-bystritsky","html_url":"https:\/\/github.com\/magento\/magento2\/pull\/11876","repo":"magento\/magento2","state":"merged","title":"After logging in customer is now not redirecting to Customer Dashboard by default"},"11817":{"created":"2017-10-27T14:34:58Z","author":"p-bystritsky","html_url":"https:\/\/github.com\/magento\/magento2\/pull\/11817","repo":"magento\/magento2","state":"merged","title":"GITHUB-8970: Cannot assign products to categories not under tree root."},"11779":{"created":"2017-10-26T15:34:54Z","author":"p-bystritsky","html_url":"https:\/\/github.com\/magento\/magento2\/pull\/11779","repo":"magento\/magento2","state":"merged","title":"MAGETWO-4711: Improve error reporting for products images import."},"11732":{"created":"2017-10-25T15:28:07Z","author":"p-bystritsky","html_url":"https:\/\/github.com\/magento\/magento2\/pull\/11732","repo":"magento\/magento2","state":"merged","title":"MAGETWO-5015: Report error csv doesn't work when trying to import a csv file with semicolon delimiter."}},"_issues":[]}