{"avatar_url":"https:\/\/avatars2.githubusercontent.com\/u\/15340849?v=4","author":"romainruaud","created":4,"closed":3,"merged":2,"rejected":1,"acceptance_rate":"67%","_pull_requests":{"11254":{"created":"2017-10-05T15:36:17Z","author":"romainruaud","html_url":"https:\/\/github.com\/magento\/magento2\/pull\/11254","repo":"magento\/magento2","state":"merged","title":"Fix for #10317 Disable region list when switching to a region optional country."},"11250":{"created":"2017-10-05T14:29:40Z","author":"romainruaud","html_url":"https:\/\/github.com\/magento\/magento2\/pull\/11250","repo":"magento\/magento2","state":"merged","title":"Fixing #10275 keyboard submit of adminhtml suggest form."},"11222":{"created":"2017-10-04T14:24:14Z","author":"romainruaud","html_url":"https:\/\/github.com\/magento\/magento2\/pull\/11222","repo":"magento\/magento2","state":"closed","title":"Ability to connect to Redis Sentinel for Cache, PageCache and Session"},"10694":{"created":"2017-08-29T10:57:35Z","author":"romainruaud","html_url":"https:\/\/github.com\/magento\/magento2\/pull\/10694","repo":"magento\/magento2","state":"closed","title":"Fix #10693 : Use Distro Base Url if configuration value has been prev\u2026"}},"_issues":{"12100":{"created":"2017-11-08T10:37:41Z","html_url":"https:\/\/github.com\/magento\/magento2\/issues\/12100","repo":"magento\/magento2","state":"open","title":"Compilation not generating factories declared in di.xml"},"10962":{"created":"2017-09-19T13:57:03Z","html_url":"https:\/\/github.com\/magento\/magento2\/issues\/10962","repo":"magento\/magento2","state":"closed","title":"Consider credis library update to allow Redis Sentinel cluster usage"},"10881":{"created":"2017-09-14T08:36:55Z","html_url":"https:\/\/github.com\/magento\/magento2\/issues\/10881","repo":"magento\/magento2","state":"open","title":"Redis password not used when trying to validate the connection during install."},"10693":{"created":"2017-08-29T10:09:05Z","html_url":"https:\/\/github.com\/magento\/magento2\/issues\/10693","repo":"magento\/magento2","state":"closed","title":"Not able anymore to use Magento by specifying base_url placeholder"},"10421":{"created":"2017-08-03T13:34:06Z","html_url":"https:\/\/github.com\/magento\/magento2\/issues\/10421","repo":"magento\/magento2","state":"closed","title":"Missing Foreign Key \/ Cascade process for catalog_category_product_index table"},"9411":{"created":"2017-04-26T16:47:14Z","html_url":"https:\/\/github.com\/magento\/magento2\/issues\/9411","repo":"magento\/magento2","state":"closed","title":"Translate from DI does not seem to work"},"8209":{"created":"2017-01-20T10:52:46Z","html_url":"https:\/\/github.com\/magento\/magento2\/issues\/8209","repo":"magento\/magento2","state":"closed","title":"Catalog Price Rules and wrong faceting \/ sorting"}}}