{"avatar_url":"https:\/\/avatars0.githubusercontent.com\/u\/6178967?v=4","author":"southerncomputer","created":2,"closed":2,"merged":1,"rejected":1,"acceptance_rate":"50%","_pull_requests":{"9842":{"created":"2017-06-03T15:30:43Z","author":"southerncomputer","html_url":"https:\/\/github.com\/magento\/magento2\/pull\/9842","repo":"magento\/magento2","state":"closed","title":"Fix broken Parallel deploy for redis users"},"9723":{"created":"2017-05-21T19:08:56Z","author":"southerncomputer","html_url":"https:\/\/github.com\/magento\/magento2\/pull\/9723","repo":"magento\/magento2","state":"merged","title":"Patch to allow multiple filter_url_params to function"}},"_issues":{"11171":{"created":"2017-10-01T14:05:16Z","html_url":"https:\/\/github.com\/magento\/magento2\/issues\/11171","repo":"magento\/magento2","state":"closed","title":"If you find your javascript bundling broken every night ->  VIRUS NAME: Html.Exploit.CVE_2017_8750-6336209-0 TDB: Engine:55-255,Target:3 LOGICAL EXPRESSION: 0&1  * SUBSIG ID 0  +-> OFFSET: ANY  +-> SIGMOD: NONE  +-> DECODED SUBSIGNATURE: weakmap()"}}}