{"avatar_url":"https:\/\/avatars2.githubusercontent.com\/u\/1165302?v=4","author":"tdgroot","created":5,"closed":5,"merged":5,"rejected":0,"acceptance_rate":"100%","_pull_requests":{"11702":{"created":"2017-10-24T18:12:05Z","author":"tdgroot","html_url":"https:\/\/github.com\/magento\/magento2\/pull\/11702","repo":"magento\/magento2","state":"merged","title":"Fix getReservedOrderId() to use current store instead of default store"},"11686":{"created":"2017-10-24T12:20:34Z","author":"tdgroot","html_url":"https:\/\/github.com\/magento\/magento2\/pull\/11686","repo":"magento\/magento2","state":"merged","title":" Fix error when generating urn catalog for empty misc.xml"},"10151":{"created":"2017-07-05T10:25:17Z","author":"tdgroot","html_url":"https:\/\/github.com\/magento\/magento2\/pull\/10151","repo":"magento\/magento2","state":"merged","title":"Fix Widget saving non-XML entities to layout_update"},"9348":{"created":"2017-04-21T18:22:24Z","author":"tdgroot","html_url":"https:\/\/github.com\/magento\/magento2\/pull\/9348","repo":"magento\/magento2","state":"merged","title":"Replace framework's Zend_Session interface usage with SessionHandlerInterface"},"9285":{"created":"2017-04-17T21:04:23Z","author":"tdgroot","html_url":"https:\/\/github.com\/magento\/magento2\/pull\/9285","repo":"magento\/magento2","state":"merged","title":"Replace Zend_Log with Psr\\Log\\LoggerInterface"}},"_issues":{"11318":{"created":"2017-10-09T18:00:35Z","html_url":"https:\/\/github.com\/magento\/magento2\/issues\/11318","repo":"magento\/magento2","state":"closed","title":"Feature: extra arguments for setup:config:set"}}}