{"avatar_url":"https:\/\/avatars2.githubusercontent.com\/u\/771236?v=4","author":"chicgeek","created":2,"closed":1,"merged":0,"rejected":1,"acceptance_rate":"0%","_pull_requests":{"1988":{"created":"2015-09-30T13:54:11Z","author":"chicgeek","html_url":"https:\/\/github.com\/magento\/magento2\/pull\/1988","repo":"magento\/magento2","state":"merged","title":"Use inline elements for inline links"},"1733":{"created":"2015-08-24T18:22:21Z","author":"chicgeek","html_url":"https:\/\/github.com\/magento\/magento2\/pull\/1733","repo":"magento\/magento2","state":"closed","title":"Allow user zoom"}},"_issues":{"1970":{"created":"2015-09-28T11:44:25Z","html_url":"https:\/\/github.com\/magento\/magento2\/issues\/1970","repo":"magento\/magento2","state":"closed","title":"Unable to override knockout templates for form elements"},"1821":{"created":"2015-09-08T16:00:48Z","html_url":"https:\/\/github.com\/magento\/magento2\/issues\/1821","repo":"magento\/magento2","state":"closed","title":"CSS load order incorrect using default_head_blocks.xml"}}}