{"avatar_url":"https:\/\/avatars1.githubusercontent.com\/u\/489806?v=4","author":"daniel-rose","created":2,"closed":2,"merged":1,"rejected":1,"acceptance_rate":"50%","_pull_requests":{"1834":{"created":"2015-09-10T10:25:11Z","author":"daniel-rose","html_url":"https:\/\/github.com\/magento\/magento2\/pull\/1834","repo":"magento\/magento2","state":"closed","title":"Use the correct access modifier for the abstract method \"execute\""},"1818":{"created":"2015-09-08T12:38:57Z","author":"daniel-rose","html_url":"https:\/\/github.com\/magento\/magento2\/pull\/1818","repo":"magento\/magento2","state":"merged","title":"use return value instead of reference parameter"}},"_issues":[]}