{"avatar_url":"https:\/\/avatars3.githubusercontent.com\/u\/2690391?v=4","author":"tahiryasin","created":3,"closed":3,"merged":3,"rejected":0,"acceptance_rate":"100%","_pull_requests":{"444":{"created":"2015-12-11T12:32:17Z","author":"tahiryasin","html_url":"https:\/\/github.com\/magento\/devdocs\/pull\/444","repo":"magento\/devdocs","state":"merged","title":"Missing table added"},"441":{"created":"2015-12-09T11:15:23Z","author":"tahiryasin","html_url":"https:\/\/github.com\/magento\/devdocs\/pull\/441","repo":"magento\/devdocs","state":"merged","title":"mistakes corrected"},"392":{"created":"2015-10-22T11:14:51Z","author":"tahiryasin","html_url":"https:\/\/github.com\/magento\/devdocs\/pull\/392","repo":"magento\/devdocs","state":"merged","title":"Corrections made"}},"_issues":{"2402":{"created":"2015-11-18T10:35:48Z","html_url":"https:\/\/github.com\/magento\/magento2\/issues\/2402","repo":"magento\/magento2","state":"closed","title":"Unable to create new category"}}}