{"avatar_url":"https:\/\/avatars1.githubusercontent.com\/u\/3738135?v=4","author":"allanpaiste","created":7,"closed":2,"merged":0,"rejected":2,"acceptance_rate":"0%","_pull_requests":{"6202":{"created":"2016-08-17T15:54:13Z","author":"allanpaiste","html_url":"https:\/\/github.com\/magento\/magento2\/pull\/6202","repo":"magento\/magento2","state":"closed","title":"Move PageCache session form_key reset to trigger only for frontend area"},"6085":{"created":"2016-08-09T21:04:04Z","author":"allanpaiste","html_url":"https:\/\/github.com\/magento\/magento2\/pull\/6085","repo":"magento\/magento2","state":"closed","title":"Catalog rules: Convert multiselect varchar values to correct format"},"6083":{"created":"2016-08-09T19:17:00Z","author":"allanpaiste","html_url":"https:\/\/github.com\/magento\/magento2\/pull\/6083","repo":"magento\/magento2","state":"closed","title":"Correctly html-decode all widget options (even when they're arrays)"},"6038":{"created":"2016-08-07T19:32:29Z","author":"allanpaiste","html_url":"https:\/\/github.com\/magento\/magento2\/pull\/6038","repo":"magento\/magento2","state":"closed","title":"Fix to product-list widget not rendering 'rules' correctly when re-configured in WYSIWYG form"},"6035":{"created":"2016-08-07T16:09:30Z","author":"allanpaiste","html_url":"https:\/\/github.com\/magento\/magento2\/pull\/6035","repo":"magento\/magento2","state":"closed","title":"Make product list filter counts dependent on product visibility configuration"},"5978":{"created":"2016-08-04T07:36:47Z","author":"allanpaiste","html_url":"https:\/\/github.com\/magento\/magento2\/pull\/5978","repo":"magento\/magento2","state":"closed","title":"Category 'image' attribute type implementation to work with any attribute code"},"5970":{"created":"2016-08-03T17:49:19Z","author":"allanpaiste","html_url":"https:\/\/github.com\/magento\/magento2\/pull\/5970","repo":"magento\/magento2","state":"closed","title":"Fix\/image type category eav attribute"}},"_issues":{"6201":{"created":"2016-08-17T15:40:38Z","html_url":"https:\/\/github.com\/magento\/magento2\/issues\/6201","repo":"magento\/magento2","state":"closed","title":"Admin gets redirected to dashboard"}}}