{"avatar_url":"https:\/\/avatars2.githubusercontent.com\/u\/6109662?v=4","author":"mathewhellums","created":2,"closed":1,"merged":0,"rejected":1,"acceptance_rate":"0%","_pull_requests":{"6216":{"created":"2016-08-18T04:12:01Z","author":"mathewhellums","html_url":"https:\/\/github.com\/magento\/magento2\/pull\/6216","repo":"magento\/magento2","state":"closed","title":"Fixed popular search terms not displaying on frontend."},"6191":{"created":"2016-08-17T04:31:49Z","author":"mathewhellums","html_url":"https:\/\/github.com\/magento\/magento2\/pull\/6191","repo":"magento\/magento2","state":"closed","title":"Added Puerto Rico to the Directory module's install data script."}},"_issues":[]}