{"avatar_url":"https:\/\/avatars2.githubusercontent.com\/u\/10513307?v=4","author":"tkn98","created":3,"closed":1,"merged":1,"rejected":0,"acceptance_rate":"100%","_pull_requests":{"5859":{"created":"2016-07-28T12:05:36Z","author":"tkn98","html_url":"https:\/\/github.com\/magento\/magento2\/pull\/5859","repo":"magento\/magento2","state":"closed","title":"Cast string SKUs back to string"},"5518":{"created":"2016-07-07T12:11:07Z","author":"tkn98","html_url":"https:\/\/github.com\/magento\/magento2\/pull\/5518","repo":"magento\/magento2","state":"closed","title":"Remove superfluous realpath call"},"3360":{"created":"2016-02-10T13:46:51Z","author":"tkn98","html_url":"https:\/\/github.com\/magento\/magento2\/pull\/3360","repo":"magento\/magento2","state":"merged","title":"Improve developer exception HTTP response"}},"_issues":{"5488":{"created":"2016-07-06T07:09:19Z","html_url":"https:\/\/github.com\/magento\/magento2\/issues\/5488","repo":"magento\/magento2","state":"closed","title":"Wording: Please re-run Magento compile command - Incorrect command name"},"4383":{"created":"2016-05-03T08:02:13Z","html_url":"https:\/\/github.com\/magento\/magento2\/issues\/4383","repo":"magento\/magento2","state":"closed","title":"Error composer install on EE 2.0.5, MAGETWO-52431"},"4375":{"created":"2016-05-02T12:03:55Z","html_url":"https:\/\/github.com\/magento\/magento2\/issues\/4375","repo":"magento\/magento2","state":"closed","title":"Integration tests don't work after checkout"},"3720":{"created":"2016-03-10T16:33:58Z","html_url":"https:\/\/github.com\/magento\/magento2\/issues\/3720","repo":"magento\/magento2","state":"closed","title":"Fulltext CatalogSearch update deletes from non-existent table(s)"},"3529":{"created":"2016-02-24T13:20:36Z","html_url":"https:\/\/github.com\/magento\/magento2\/issues\/3529","repo":"magento\/magento2","state":"closed","title":"Database port missing in Magento\\TestFramework\\Db\\Mysql"},"3232":{"created":"2016-02-01T11:02:51Z","html_url":"https:\/\/github.com\/magento\/magento2\/issues\/3232","repo":"magento\/magento2","state":"closed","title":"Current Config Scope shows as \"disabled\" \/ \"non-selectable\" while it is active"},"3176":{"created":"2016-01-28T09:56:58Z","html_url":"https:\/\/github.com\/magento\/magento2\/issues\/3176","repo":"magento\/magento2","state":"closed","title":"What is the rationale to have a BlockInterface when AbstractBlock is required (in Fw\\View ?)"},"2985":{"created":"2016-01-13T14:13:06Z","html_url":"https:\/\/github.com\/magento\/magento2\/issues\/2985","repo":"magento\/magento2","state":"closed","title":"What is the rationale behind making BaseTestCase::setUp() public"}}}